<?xml version="1.0" encoding="UTF-8"?>
<mapping xmlns:xsd="http://www.w3.org/2001/XMLSchema" xmlns:cgu="urn:cgi:xmlns:CGI:Utilities:1.0"
	xmlns:xsi="http://www.w3.org/2001/XMLSchema-instance" xmlns="urn:tbd:xmlns:TBD:FullMoon:type-mapping:1.0"
	xsi:schemaLocation="urn:tbd:xmlns:TBD:FullMoon:type-mapping:1.0 ../../../../resources/type-mapping-util/type-mapping.xsd"
	id="ClassMap_ISO_19115_Metadata.xml">
	<description>Provides a mapping of the classes in the SWE Common model to their implementation in the http://www.opengis.net/swe/1.0.1 XML Schema</description>
	<entry>
		<umlClass>CI_Citation</umlClass>
		<gmlObjectElement xsi:nil="true"/>
		<gmlType xsi:nil="true"/>
		<gmlPropertyType>cgu:WildCardPropertyType</gmlPropertyType>
	</entry>
	<entry>
		<umlClass>CI_ResponsibleParty</umlClass>
		<gmlObjectElement xsi:nil="true"/>
		<gmlType xsi:nil="true"/>
		<gmlPropertyType>cgu:WildCardPropertyType</gmlPropertyType>
	</entry>
	<entry>
		<umlClass>DQ_Quality</umlClass>
		<gmlObjectElement xsi:nil="true"/>
		<gmlType xsi:nil="true"/>
		<gmlPropertyType>cgu:WildCardPropertyType</gmlPropertyType>
	</entry>
	<entry>
		<umlClass>DQ_ThematicAccuracy</umlClass>
		<gmlObjectElement xsi:nil="true"/>
		<gmlType xsi:nil="true"/>
		<gmlPropertyType>cgu:WildCardPropertyType</gmlPropertyType>
	</entry>
	<entry>
		<umlClass>EX_Extent</umlClass>
		<gmlObjectElement xsi:nil="true"/>
		<gmlType xsi:nil="true"/>
		<gmlPropertyType>cgu:WildCardPropertyType</gmlPropertyType>
	</entry>
</mapping>
